<?xml version="1.0" encoding="UTF-8"?>
<objects serializationModel="Studio.01.10.00">
    <object class="AudioFile" id="{7ef04cf8-0d32-48c9-8e23-8e1094775da7}">
        <property name="assetPath">
            <value>Fx_Hab_Trueno 2_v1_MN.L.wav</value>
        </property>
        <property name="frequencyInKHz">
            <value>48</value>
        </property>
        <property name="channelCount">
            <value>1</value>
        </property>
        <property name="length">
            <value>18.901062499999998</value>
        </property>
        <relationship name="masterAssetFolder">
            <destination>{222c4da8-e78e-433f-8000-a7363550ee76}</destination>
        </relationship>
    </object>
</objects>
